{
    "total": 163,
    "data": [
        {
            "category": "Buah",
            "total": 43,
            "data": {
                "B001": {
                    "total": 15,
                    "data": [
                        {
                            "name": "Apel",
                            "total": 10
                        },
                        {
                            "name": "Anggur",
                            "total": 5
                        }
                    ]
                },
                "B002": {
                    "total": 28,
                    "data": [
                        {
                            "name": "Pepaya",
                            "total": 20
                        },
                        {
                            "name": "Pisang",
                            "total": 8
                        }
                    ]
                }
            }
        },
        {
            "category": "Hewan",
            "total": 65,
            "data": {
                "H001": {
                    "total": 40,
                    "data": [
                        {
                            "name": "Kucing",
                            "total": 30
                        },
                        {
                            "name": "Harimau",
                            "total": 10
                        }
                    ]
                },
                "H002": {
                    "total": 25,
                    "data": [
                        {
                            "name": "Buaya",
                            "total": 10
                        },
                        {
                            "name": "Komodo",
                            "total": 15
                        }
                    ]
                }
            }
        },
        {
            "category": "Sayuran",
            "total": 55,
            "data": {
                "S001": {
                    "total": 12,
                    "data": [
                        {
                            "name": "Bayam",
                            "total": 12
                        }
                    ]
                },
                "S002": {
                    "total": 18,
                    "data": [
                        {
                            "name": "Kangkung",
                            "total": 18
                        }
                    ]
                },
                "S003": {
                    "total": 25,
                    "data": [
                        {
                            "name": "Wortel",
                            "total": 25
                        }
                    ]
                }
            }
        }
    ]
}